todo_catalog/__init__.py
todo_catalog/catalog.py
todo_catalog-0.1.1.dist-info/AUTHORS.rst
todo_catalog-0.1.1.dist-info/LICENSE.txt
todo_catalog-0.1.1.dist-info/METADATA
todo_catalog-0.1.1.dist-info/WHEEL
todo_catalog-0.1.1.dist-info/entry_points.txt
todo_catalog-0.1.1.dist-info/top_level.txt
todo_catalog-0.1.1.dist-info/RECORD
